bidet/__init__.py
bidet-0.0.3.dist-info/LICENSE
bidet-0.0.3.dist-info/METADATA
bidet-0.0.3.dist-info/WHEEL
bidet-0.0.3.dist-info/top_level.txt
bidet-0.0.3.dist-info/RECORD
